{
	"crop.json": "crop.json",
	"site.json": "site.json",
	"climate.csv": "",

	"climate.csv-options": {
        "no-of-climate-file-header-lines": 2,
        "csv-separator": ",",
        "header-to-acd-names": {
			"windspeed": "wind"
        }
    },
	
	"debug?": false,
	"path-to-output": "./",
	"include-file-base-path": "/will/be/overwritten/path/to/monica/parameters",
	
	"output": { 
	  "write-file?": false,
		"file-name": "out.csv",
	
		"csv-options": {
			"include-header-row": true,
			"include-units-row": false,
			"csv-separator": ","
		},

		"obj-outputs?": true,

		"nc-events": [			
			"Sowing", [
				["DOY|Sowing-DOY", "FIRST"],
				["Mois|Sowing-avg-sm-0-30", [1, 3, "AVG"]],
				["Mois|Sowing-avg-sm-30-60", [4, 6, "AVG"]],
				["Mois|Sowing-avg-sm-60-90", [7, 9, "AVG"]]
			],
			"Stage-2", [
				"DOY|Stage-2-DOY",
				["Mois|Stage-2-avg-sm-0-30", [1, 3, "AVG"]],
				["Mois|Stage-2-avg-sm-30-60", [4, 6, "AVG"]],
				["Mois|Stage-2-avg-sm-60-90", [7, 9, "AVG"]]
			],
			"stem-elongation", [
				"DOY|Cereal-stem-elongation-DOY",
				["Mois|Cereal-stem-elongation-avg-sm-0-30", [1, 3, "AVG"]],
				["Mois|Cereal-stem-elongation-avg-sm-30-60", [4, 6, "AVG"]],
				["Mois|Cereal-stem-elongation-avg-sm-60-90", [7, 9, "AVG"]]
			],
			"Stage-3", [
				"DOY|Stage-3-DOY",
				["Mois|Stage-3-avg-sm-0-30", [1, 3, "AVG"]],
				["Mois|Stage-3-avg-sm-30-60", [4, 6, "AVG"]],
				["Mois|Stage-3-avg-sm-60-90", [7, 9, "AVG"]]
			],
			"Stage-4", [
				"DOY|Stage-4-DOY",
				["Mois|Stage-4-avg-sm-0-30", [1, 3, "AVG"]],
				["Mois|Stage-4-avg-sm-30-60", [4, 6, "AVG"]],
				["Mois|Stage-4-avg-sm-60-90", [7, 9, "AVG"]]
			],
			"Stage-5", [
				"DOY|Stage-5-DOY",
				["Mois|Stage-5-avg-sm-0-30", [1, 3, "AVG"]],
				["Mois|Stage-5-avg-sm-30-60", [4, 6, "AVG"]],
				["Mois|Stage-5-avg-sm-60-90", [7, 9, "AVG"]]
			],
			"Stage-6", [
				"DOY|Stage-6-DOY",
				["Mois|Stage-6-avg-sm-0-30", [1, 3, "AVG"]],
				["Mois|Stage-6-avg-sm-30-60", [4, 6, "AVG"]],
				["Mois|Stage-6-avg-sm-60-90", [7, 9, "AVG"]]
			],
			"Stage-7", [
				"DOY|Stage-7-DOY",
				["Mois|Stage-7-avg-sm-0-30", [1, 3, "AVG"]],
				["Mois|Stage-7-avg-sm-30-60", [4, 6, "AVG"]],
				["Mois|Stage-7-avg-sm-60-90", [7, 9, "AVG"]]
			],
			"Harvest", [
				["DOY|Harvest-DOY", "LAST"],
				["Mois|Harvest-avg-sm-0-30", [1, 3, "AVG"]],
				["Mois|Harvest-avg-sm-30-60", [4, 6, "AVG"]],
				["Mois|Harvest-avg-sm-60-90", [7, 9, "AVG"]]
			]
		],

		"nc-bgr-events": [	
			"daily", [
				["Mois", [1, 20]],
				["STemp", [1, 20]]
			]
		],

		"events": [			
			"crop", [
				["CM-count", "FIRST"],
				["Crop", "FIRST"],
				["DOY|Sowing-DOY", "FIRST"],
				["Year", "LAST"],
				["Mois|Sowing-avg-sm-0-30", [1, 3, "AVG"]],
				["Mois|Sowing-avg-sm-30-60", [4, 6, "AVG"]],
				["Mois|Sowing-avg-sm-60-90", [7, 9, "AVG"]],
				["DOY|Harvest-DOY", "LAST"],
				["Mois|Harvest-avg-sm-0-30", [1, 3, "AVG"]],
				["Mois|Harvest-avg-sm-30-60", [4, 6, "AVG"]],
				["Mois|Harvest-avg-sm-60-90", [7, 9, "AVG"]]
			],
			"Stage-2", [
				"CM-count",
				"DOY|Stage-2-DOY",
				"Year",
				["Mois|Stage-2-avg-sm-0-30", [1, 3, "AVG"]],
				["Mois|Stage-2-avg-sm-30-60", [4, 6, "AVG"]],
				["Mois|Stage-2-avg-sm-60-90", [7, 9, "AVG"]]
			],
			"Stage-3", [
				"CM-count",
				"DOY|Stage-3-DOY",
				"Year",
				["Mois|Stage-3-avg-sm-0-30", [1, 3, "AVG"]],
				["Mois|Stage-3-avg-sm-30-60", [4, 6, "AVG"]],
				["Mois|Stage-3-avg-sm-60-90", [7, 9, "AVG"]]
			],
			"Stage-4", [
				"CM-count",
				"DOY|Stage-4-DOY",
				"Year",
				["Mois|Stage-4-avg-sm-0-30", [1, 3, "AVG"]],
				["Mois|Stage-4-avg-sm-30-60", [4, 6, "AVG"]],
				["Mois|Stage-4-avg-sm-60-90", [7, 9, "AVG"]]
			],
			"Stage-5", [
				"CM-count",
				"DOY|Stage-5-DOY",
				"Year",
				["Mois|Stage-5-avg-sm-0-30", [1, 3, "AVG"]],
				["Mois|Stage-5-avg-sm-30-60", [4, 6, "AVG"]],
				["Mois|Stage-5-avg-sm-60-90", [7, 9, "AVG"]]
			],
			"Stage-6", [
				"CM-count",
				"DOY|Stage-6-DOY",
				"Year",
				["Mois|Stage-6-avg-sm-0-30", [1, 3, "AVG"]],
				["Mois|Stage-6-avg-sm-30-60", [4, 6, "AVG"]],
				["Mois|Stage-6-avg-sm-60-90", [7, 9, "AVG"]]
			],
			"Stage-7", [
				"CM-count",
				"DOY|Stage-7-DOY",
				"Year",
				["Mois|Stage-7-avg-sm-0-30", [1, 3, "AVG"]],
				["Mois|Stage-7-avg-sm-30-60", [4, 6, "AVG"]],
				["Mois|Stage-7-avg-sm-60-90", [7, 9, "AVG"]]
			],
			"cereal-stem-elongation", [
				"CM-count",
				"DOY|stem-elongation-DOY",
				"Year",
				["Mois|Stage-8-avg-sm-0-30", [1, 3, "AVG"]],
				["Mois|Stage-8-avg-sm-30-60", [4, 6, "AVG"]],
				["Mois|Stage-8-avg-sm-60-90", [7, 9, "AVG"]]
			]
		],

		"bgr-events": [	
			"daily", [
				"Date",
				"DOY",
				"Year",
				["Mois", [1, 20]],
				["STemp", [1, 20]]
			]
		]
	},

	"NumberOfLayers": 20,
	"LayerThickness": [0.1, "m"],

	"UseSecondaryYields": false,
	"NitrogenResponseOn": true,
	"WaterDeficitResponseOn": true,
	"EmergenceMoistureControlOn": false,
	"EmergenceFloodingControlOn": false,

	"UseAutomaticIrrigation": false,
	"AutoIrrigationParams": {
		"irrigationParameters": {
			"nitrateConcentration": [0, "mg dm-3"],
			"sulfateConcentration": [0, "mg dm-3"]
		},
		"amount": [0, "mm"],
		"threshold": 0.9
	},

	"UseNMinMineralFertilisingMethod": true,
	"NMinUserParams": { "min": 40, "max": 120, "delayInDays": 10 },
	"NMinFertiliserPartition": ["include-from-file", "mineral-fertilisers/AN.json"],
	"JulianDayAutomaticFertilising": 89
}
